<Dataset identifier="_show install committed summary">
	<Title>show install committed summary</Title>
	<Description>Mandatory,SMU Data</Description>
	<CategoryName>CLI-Inventory</CategoryName>
	<CollectionType>CLI</CollectionType>
	<VersionedDatasetList>
		<VersionedDataset identifier="_IOS_XR">
			<CLI>
				<Command>show install committed summary</Command>
				<IntegrityRule>_CNC_GLOBAL_INTEG_RULE</IntegrityRule>
			</CLI>
		</VersionedDataset>
		<VersionedDataset identifier="_IOS_XR_8000">
			<CLI>
				<Command>show install committed summary</Command>
				<IntegrityRule>_CNC_GLOBAL_INTEG_RULE</IntegrityRule>
			</CLI>
		</VersionedDataset>
		<VersionedDataset identifier="_IOS_XR_1">
			<CLI>
				<Command>show install committed summary</Command>
				<IntegrityRule>_CNC_GLOBAL_INTEG_RULE</IntegrityRule>
			</CLI>
		</VersionedDataset>
	</VersionedDatasetList>
</Dataset>
